consulate/__init__.py
consulate/adapters.py
consulate/cli.py
consulate/client.py
consulate/exceptions.py
consulate/utils.py
consulate/api/__init__.py
consulate/api/acl.py
consulate/api/agent.py
consulate/api/base.py
consulate/api/catalog.py
consulate/api/coordinate.py
consulate/api/event.py
consulate/api/health.py
consulate/api/kv.py
consulate/api/lock.py
consulate/api/session.py
consulate/api/status.py
consulate/models/__init__.py
consulate/models/acl.py
consulate/models/agent.py
consulate/models/base.py
consulate_fork-0.7.1.dist-info/LICENSE
consulate_fork-0.7.1.dist-info/METADATA
consulate_fork-0.7.1.dist-info/WHEEL
consulate_fork-0.7.1.dist-info/entry_points.txt
consulate_fork-0.7.1.dist-info/top_level.txt
consulate_fork-0.7.1.dist-info/zip-safe
consulate_fork-0.7.1.dist-info/RECORD
